.coveragerc
.gitignore
CHANGELOG.rst
LICENSE.txt
MANIFEST.in
README.md
ast-ari-py.iml
nose.cfg
setup.cfg
setup.py
ari/__init__.py
ari/client.py
ari/model.py
ari_test/__init__.py
ari_test/client_test.py
ari_test/utils.py
ari_test/websocket_test.py
codet_ari.egg-info/PKG-INFO
codet_ari.egg-info/SOURCES.txt
codet_ari.egg-info/dependency_links.txt
codet_ari.egg-info/requires.txt
codet_ari.egg-info/top_level.txt
examples/bridge_example.py
examples/cleanup_example.py
examples/example.py
examples/originate_example.py
examples/playback_example.py
sample-api/README.md
sample-api/applications.json
sample-api/asterisk.json
sample-api/bridges.json
sample-api/channels.json
sample-api/deviceStates.json
sample-api/endpoints.json
sample-api/events.json
sample-api/mailboxes.json
sample-api/playbacks.json
sample-api/recordings.json
sample-api/resources.json
sample-api/sounds.json